phy_RX/probador_RX.v
module probador_RX(output reg serial_data_0,
					output reg serial_data_1,
					output reg reset,
					output reg clk_32f,
					output reg clk_4f,
					output reg clk_2f,
					input [31:0] data_final,
					input valid_final);
	initial begin
	$dumpfile("RX.vcd");
	$dumpvars;

	serial_data_0<=0;
	serial_data_1<=0;
	reset <=0;
	
	//primer BC
	@(posedge clk_4f);
	reset <= 0;
	serial_data_0<=1;
	serial_data_1<=1;
	@(posedge clk_32f);
	serial_data_0<=0;
	serial_data_1<=0;
	@(posedge clk_32f);
	serial_data_0<=1;
	serial_data_1<=1;
	@(posedge clk_32f);
	serial_data_0<=1;
	serial_data_1<=1;
	@(posedge clk_32f);
	serial_data_0<=1;
	serial_data_1<=1;
	@(posedge clk_32f);
	serial_data_0<=1;
	serial_data_1<=1;
	@(posedge clk_32f);
	serial_data_0<=0;
	serial_data_1<=0;
	@(posedge clk_32f);
	serial_data_0<=0;
	serial_data_1<=0;

	//Segundo BC
	@(posedge clk_4f);
	serial_data_0<=1;
	serial_data_1<=1;
	@(posedge clk_32f);
	serial_data_0<=0;
	serial_data_1<=0;
	@(posedge clk_32f);
	serial_data_0<=1;
	serial_data_1<=1;
	@(posedge clk_32f);
	serial_data_0<=1;
	serial_data_1<=1;
	@(posedge clk_32f);
	serial_data_0<=1;
	serial_data_1<=1;
	@(posedge clk_32f);
	serial_data_0<=1;
	serial_data_1<=1;
	@(posedge clk_32f);
	serial_data_0<=0;
	serial_data_1<=0;
	@(posedge clk_32f);
	serial_data_0<=0;
	serial_data_1<=0;

	//Tercer BC
	@(posedge clk_4f);
	serial_data_0<=1;
	serial_data_1<=1;
	@(posedge clk_32f);
	serial_data_0<=0;
	serial_data_1<=0;
	@(posedge clk_32f);
	serial_data_0<=1;
	serial_data_1<=1;
	@(posedge clk_32f);
	serial_data_0<=1;
	serial_data_1<=1;
	@(posedge clk_32f);
	serial_data_0<=1;
	serial_data_1<=1;
	@(posedge clk_32f);
	serial_data_0<=1;
	serial_data_1<=1;
	@(posedge clk_32f);
	serial_data_0<=0;
	serial_data_1<=0;
	@(posedge clk_32f);
	serial_data_0<=0;
	serial_data_1<=0;

	//Cuarto BC
	@(posedge clk_4f);
	serial_data_0<=1;
	serial_data_1<=1;
	reset <=1;
	@(posedge clk_32f);
	serial_data_0<=0;
	serial_data_1<=0;
	@(posedge clk_32f);
	serial_data_0<=1;
	serial_data_1<=1;
	@(posedge clk_32f);
	serial_data_0<=1;
	serial_data_1<=1;
	@(posedge clk_32f);
	serial_data_0<=1;
	serial_data_1<=1;
	@(posedge clk_32f);
	serial_data_0<=1;
	serial_data_1<=1;
	@(posedge clk_32f);
	serial_data_0<=0;
	serial_data_1<=0;
	@(posedge clk_32f);
	serial_data_0<=0;
	serial_data_1<=0;


	//Señal interes
	@(posedge clk_4f);
	serial_data_0<=1;
	serial_data_1<=1;
	@(posedge clk_32f);
	serial_data_0<=1;
	serial_data_1<=1;
	@(posedge clk_32f);
	serial_data_0<=1;
	serial_data_1<=1;
	@(posedge clk_32f);
	serial_data_0<=1;
	serial_data_1<=1;
	@(posedge clk_32f);
	serial_data_0<=1;
	serial_data_1<=1;
	@(posedge clk_32f);
	serial_data_0<=1;
	serial_data_1<=1;
	@(posedge clk_32f);
	serial_data_0<=1;
	serial_data_1<=1;
	@(posedge clk_32f);
	serial_data_0<=1;
	serial_data_1<=1;

	@(posedge clk_4f);
	serial_data_0<=1;
	serial_data_1<=1;
	@(posedge clk_32f);
	serial_data_0<=1;
	serial_data_1<=1;
	@(posedge clk_32f);
	serial_data_0<=1;
	serial_data_1<=1;
	@(posedge clk_32f);
	serial_data_0<=1;
	serial_data_1<=1;
	@(posedge clk_32f);
	serial_data_0<=1;
	serial_data_1<=1;
	@(posedge clk_32f);
	serial_data_0<=1;
	serial_data_1<=1;
	@(posedge clk_32f);
	serial_data_0<=1;
	serial_data_1<=1;
	@(posedge clk_32f);
	serial_data_0<=1;
	serial_data_1<=1;

	@(posedge clk_4f);
	serial_data_0<=1;
	serial_data_1<=1;
	@(posedge clk_32f);
	serial_data_0<=1;
	serial_data_1<=1;
	@(posedge clk_32f);
	serial_data_0<=1;
	serial_data_1<=1;
	@(posedge clk_32f);
	serial_data_0<=1;
	serial_data_1<=1;
	@(posedge clk_32f);
	serial_data_0<=1;
	serial_data_1<=1;
	@(posedge clk_32f);
	serial_data_0<=1;
	serial_data_1<=1;
	@(posedge clk_32f);
	serial_data_0<=1;
	serial_data_1<=1;
	@(posedge clk_32f);
	serial_data_0<=1;
	serial_data_1<=1;

	@(posedge clk_4f);
	serial_data_0<=1;
	serial_data_1<=1;
	@(posedge clk_32f);
	serial_data_0<=1;
	serial_data_1<=1;
	@(posedge clk_32f);
	serial_data_0<=1;
	serial_data_1<=1;
	@(posedge clk_32f);
	serial_data_0<=1;
	serial_data_1<=1;
	@(posedge clk_32f);
	serial_data_0<=1;
	serial_data_1<=1;
	@(posedge clk_32f);
	serial_data_0<=1;
	serial_data_1<=1;
	@(posedge clk_32f);
	serial_data_0<=1;
	serial_data_1<=1;
	@(posedge clk_32f);
	serial_data_0<=1;
	serial_data_1<=1;

	@(posedge clk_4f);
	serial_data_0<=1;
	serial_data_1<=1;
	@(posedge clk_32f);
	serial_data_0<=1;
	serial_data_1<=1;
	@(posedge clk_32f);
	serial_data_0<=1;
	serial_data_1<=1;
	@(posedge clk_32f);
	serial_data_0<=1;
	serial_data_1<=1;
	@(posedge clk_32f);
	serial_data_0<=0;
	serial_data_1<=0;
	@(posedge clk_32f);
	serial_data_0<=0;
	serial_data_1<=0;
	@(posedge clk_32f);
	serial_data_0<=0;
	serial_data_1<=0;
	@(posedge clk_32f);
	serial_data_0<=0;
	serial_data_1<=0;

	@(posedge clk_4f);
	serial_data_0<=1;
	serial_data_1<=1;
	@(posedge clk_32f);
	serial_data_0<=1;
	serial_data_1<=1;
	@(posedge clk_32f);
	serial_data_0<=1;
	serial_data_1<=1;
	@(posedge clk_32f);
	serial_data_0<=1;
	serial_data_1<=1;
	@(posedge clk_32f);
	serial_data_0<=0;
	serial_data_1<=0;
	@(posedge clk_32f);
	serial_data_0<=0;
	serial_data_1<=0;
	@(posedge clk_32f);
	serial_data_0<=0;
	serial_data_1<=0;
	@(posedge clk_32f);
	serial_data_0<=0;
	serial_data_1<=0;
	
	@(posedge clk_4f);
	serial_data_0<=0;
	serial_data_1<=0;
	@(posedge clk_32f);
	serial_data_0<=0;
	serial_data_1<=0;
	@(posedge clk_32f);
	serial_data_0<=0;
	serial_data_1<=0;
	@(posedge clk_32f);
	serial_data_0<=0;
	serial_data_1<=0;
	@(posedge clk_32f);
	serial_data_0<=1;
	serial_data_1<=1;
	@(posedge clk_32f);
	serial_data_0<=1;
	serial_data_1<=1;
	@(posedge clk_32f);
	serial_data_0<=1;
	serial_data_1<=1;
	@(posedge clk_32f);
	serial_data_0<=1;
	serial_data_1<=1;

	@(posedge clk_4f);
	serial_data_0<=0;
	serial_data_1<=0;
	@(posedge clk_32f);
	serial_data_0<=0;
	serial_data_1<=0;
	@(posedge clk_32f);
	serial_data_0<=0;
	serial_data_1<=0;
	@(posedge clk_32f);
	serial_data_0<=0;
	serial_data_1<=0;
	@(posedge clk_32f);
	serial_data_0<=1;
	serial_data_1<=1;
	@(posedge clk_32f);
	serial_data_0<=1;
	serial_data_1<=1;
	@(posedge clk_32f);
	serial_data_0<=1;
	serial_data_1<=1;
	@(posedge clk_32f);
	serial_data_0<=1;
	serial_data_1<=1;

	@(posedge clk_4f);
	serial_data_0<=1;
	serial_data_1<=1;
	$finish;
	end
	
	initial clk_2f <= 1;
	always #16 clk_2f <= ~clk_2f;

	initial clk_4f <= 1;
	always #8 clk_4f <= ~clk_4f;

	initial clk_32f <= 1;
	always #1 clk_32f <= ~clk_32f;
endmodule

mux_striping/mux_striping.v
module mux_striping(
	input clk_2f,
	input [31:0] lane_0,
	input [31:0] lane_1,
	input valid_0,
    input valid_1,
	input reset,
	output reg [31:0] data_output,
    output reg  valid_out
    );
    reg sel;

	always @(posedge clk_2f) begin
		if(reset == 0)begin
			sel <=0 ;
			valid_out <= 0;
		end
		else begin
			if (sel==0) begin
				if (valid_0==1)begin
					data_output<=lane_0 ;
					sel <= 1;
					valid_out<=1;
				end
				else begin
					sel <= 0;
					valid_out<=0;
				end
			end
			else begin
				if (valid_1==1) begin
					data_output<=lane_1 ;
					sel <= 0;
					valid_out<=1;
				end
				else begin
					sel <= 1;
					valid_out<=0;
				end
			end	

		end
	end

endmodule

demux_8_32/demux_8_32.v
module demux_8_32(input clk_4f,
				input [7:0] data_in,
				input valid,
				input reset,
				output reg [31:0] data_out,
				output reg valid_out); //tiene que ser reg para poder ser l-value

	reg [1:0] selector;

	always @(posedge clk_4f) begin
		if(reset == 0) begin
			selector [1:0] <= 2'b00;
			valid_out <= 0;
		end
		else begin
			if(valid == 1) begin
				if(selector == 2'b00) begin
					data_out [31:24] <= data_in;
					valid_out <= valid;
					selector <= 2'b01;
				end
				else if(selector == 2'b01) begin
					data_out [23:16] <= data_in;
					valid_out <= valid;
					selector <= 2'b10;
				end
				else if(selector[1] == 1 && selector[0] == 0) begin
					data_out [15:8] <= data_in;
					valid_out <= valid;
					selector <= 2'b11;
				end
				else if(selector == 2'b11) begin
					data_out [7:0] <= data_in;
					valid_out <= valid;
					selector <= 2'b00;
				end
			end
			else begin
				valid_out <= 0;
				selector <= 2'b00;
			end
		end
	end


endmodule

serial_paralelo/serial_paralelo.v
module serial_paralelo(
	input reset,
	input clk_4f,
	input clk_32f,
	input data_in,
	output reg [7:0] data2send,
	output reg active,
	output reg valid_out,
	output reg [7:0] data_out
	);
	reg [2:0] selector;
	reg [2:0] BC_counter;
	reg [7:0] transicion_dataout;
	reg dataout_on;

	always @(posedge clk_32f) begin
		if (reset==0)begin
			data2send [7:0]<= 8'b00000000;
			data_out [7:0]<= 8'b00000000;
			transicion_dataout [7:0]<= 8'b00000000;
			valid_out <= 0;
			active <= 0;
			selector <= 0;
			BC_counter <= 0;
			dataout_on <= 0;
		end
		else if (reset==1) begin
			case (selector)
        		0: begin
					data2send[7:7] <= data_in;
					//data2send[6:0] <= 7'b0000000;
					if (dataout_on==1) begin
						transicion_dataout[7:7] <= data_in;
					end
					else begin
						transicion_dataout[7:7] <= 0;
					end
					
				end
				
        		1: begin
					data2send[6:6] <= data_in;
					if (dataout_on==1) begin
						transicion_dataout[6:6] <= data_in;
					end
					else begin
						transicion_dataout[6:6] <= 0;
					end
				end
        		2: begin
					data2send[5:5] <= data_in;
					if (dataout_on==1) begin
						transicion_dataout[5:5] <= data_in;
					end
					else begin
						transicion_dataout[5:5] <= 0;
					end
				end
        		3: begin
					data2send[4:4] <= data_in;
					if (dataout_on==1) begin
						transicion_dataout[4:4] <= data_in;
					end
					else begin
						transicion_dataout[4:4] <= 0;
					end
				end
        		4: begin
					data2send[3:3] <= data_in;
					if (dataout_on==1) begin
						transicion_dataout[3:3] <= data_in;
					end
					else begin
						transicion_dataout[3:3] <= 0;
					end
				end
        		5: begin
					data2send[2:2] <= data_in;
					if (dataout_on==1) begin
						transicion_dataout[2:2] <= data_in;
					end
					else begin
						transicion_dataout[2:2] <= 0;
					end
				end
        		6: begin
					data2send[1:1] <= data_in;
					if (dataout_on==1) begin
						transicion_dataout[1:1] <= data_in;
					end
					else begin
						transicion_dataout[1:1] <= 0;
					end
				end
        		7: begin
					data2send[0:0] <= data_in;
					if (dataout_on==1) begin
						transicion_dataout[0:0] <= data_in;
					end
					else begin
						transicion_dataout[0:0] <= 0;
					end
				end
			endcase
		
			selector <= selector+1;
			if (selector==7) begin
				selector <= 0;
				data_out[7:0]<=transicion_dataout[7:0];
				if (data2send[7:0]==8'b10111100) begin
					BC_counter<= BC_counter+1;
					valid_out<=0;
				end
				else begin
					valid_out<=1;
				end
				if (BC_counter>3) begin
					active <= 1;
				end

				if (active ==1) begin
					dataout_on<=1; 
				end
			end
		end
		
	end
endmodule

phy_RX/phy_RX.v
`include "../serial_paralelo/serial_paralelo.v"
`include "../mux_striping/mux_striping.v"
`include "../demux_8_32/demux_8_32.v"

module phy_RX(input serial_data_0,
				input serial_data_1,
				input reset,
				input clk_2f,
				input clk_4f,
				input clk_32f,
				output [31:0] data_final,
				output valid_final);

	wire data_in0, data_in1, clk_4f, clk_32f, reset, active_0, active_1;
	wire [7:0] data2send_0, data2send_1;

	wire [7:0] data_out_0, data_out_1;

	wire [7:0] data_out_sp_0, data_out_sp_1;

	wire valid_sp_0, valid_sp_1, valid_demux_0, valid_demux_1;
	
	wire [31:0] demux_out_0, demux_out_1;

   serial_paralelo sp0 (/*AUTOINST*/
			// Outputs
			.data2send	(data2send_0[7:0]),
			.active		(active_0),
			.valid_out	(valid_out_0),
			.data_out	(data_out_sp_0[7:0]),
			// Inputs
			.reset		(reset),
			.clk_4f		(clk_4f),
			.clk_32f	(clk_32f),
			.data_in	(serial_data_0));

   serial_paralelo sp1 (/*AUTOINST*/
			// Outputs
			.data2send	(data2send_1[7:0]),
			.active		(active_1),
			.valid_out	(valid_sp_1),
			.data_out	(data_out_sp_1[7:0]),
			// Inputs
			.reset		(reset),
			.clk_4f		(clk_4f),
			.clk_32f	(clk_32f),
			.data_in	(serial_data_1));

	demux_8_32 demux_final_0 (/*AUTOINST*/
				// Outputs
				.data_out		(demux_out_0[31:0]),
				.valid_out		(valid_demux_0),
				// Inputs
				.clk_4f		(clk_4f),
				.data_in		(data_out_sp_0[7:0]),
				.valid		(valid_sp_0),
				.reset		(reset));

   demux_8_32 demux_final_1 (/*AUTOINST*/
			     // Outputs
			     .data_out		(demux_out_1[31:0]),
			     .valid_out		(valid_demux_1),
			     // Inputs
			     .clk_4f		(clk_4f),
			     .data_in		(data_out_sp_1[7:0]),
			     .valid		(valid_sp_1),
			     .reset		(reset));
   
   mux_striping mux_stp(/*AUTOINST*/
			  // Outputs
			  .data_output		(data_final[31:0]),
			  .valid_out		(valid_final),
			  // Inputs
			  .clk_2f		(clk_2f),
			  .lane_0		(demux_out_0[31:0]),
			  .lane_1		(demux_out_1[31:0]),
			  .valid_0		(valid_demux_0),
			  .valid_1		(valid_demux_1),
			  .reset		(reset));
   
endmodule

phy_RX/BancoPrueba_RX.v
`timescale 1ns/100ps
`include "phy_RX.v"
`include "probador_RX.v"

module BancoPrueba_RX;

	wire [31:0] data_final;
	wire valid_final;
	
   phy_RX RX_conductual(/*AUTOINST*/
			// Outputs
			.data_final	(data_final[31:0]),
			.valid_final	(valid_final),
			// Inputs
			.serial_data_0	(serial_data_0),
			.serial_data_1	(serial_data_1),
			.reset		(reset),
			.clk_2f		(clk_2f),
			.clk_4f		(clk_4f),
			.clk_32f	(clk_32f));

   probador_RX probador(/*AUTOINST*/
			// Outputs
			.serial_data_0	(serial_data_0),
			.serial_data_1	(serial_data_1),
			.reset		(reset),
			.clk_32f	(clk_32f),
			.clk_4f		(clk_4f),
			.clk_2f		(clk_2f),
			// Inputs
			.data_final	(data_final[31:0]),
			.valid_final	(valid_final));

endmodule

phy_RX/RX.vcd
$date
	Fri Oct  2 19:29:51 2020
$end
$version
	Icarus Verilog
$end
$timescale
	100ps
$end
$scope module BancoPrueba_RX $end
$var wire 1 ! valid_final $end
$var wire 1 " serial_data_1 $end
$var wire 1 # serial_data_0 $end
$var wire 1 $ reset $end
$var wire 32 % data_final [31:0] $end
$var wire 1 & clk_4f $end
$var wire 1 ' clk_32f $end
$var wire 1 ( clk_2f $end
$scope module RX_conductual $end
$var wire 1 ) valid_sp_0 $end
$var wire 1 * valid_sp_1 $end
$var wire 1 + valid_out_0 $end
$var wire 1 ! valid_final $end
$var wire 1 , valid_demux_1 $end
$var wire 1 - valid_demux_0 $end
$var wire 1 " serial_data_1 $end
$var wire 1 # serial_data_0 $end
$var wire 1 $ reset $end
$var wire 32 . demux_out_1 [31:0] $end
$var wire 32 / demux_out_0 [31:0] $end
$var wire 8 0 data_out_sp_1 [7:0] $end
$var wire 8 1 data_out_sp_0 [7:0] $end
$var wire 32 2 data_final [31:0] $end
$var wire 8 3 data2send_1 [7:0] $end
$var wire 8 4 data2send_0 [7:0] $end
$var wire 1 & clk_4f $end
$var wire 1 ' clk_32f $end
$var wire 1 ( clk_2f $end
$var wire 1 5 active_1 $end
$var wire 1 6 active_0 $end
$scope module demux_final_0 $end
$var wire 1 ) valid $end
$var wire 1 $ reset $end
$var wire 8 7 data_in [7:0] $end
$var wire 1 & clk_4f $end
$var reg 32 8 data_out [31:0] $end
$var reg 2 9 selector [1:0] $end
$var reg 1 - valid_out $end
$upscope $end
$scope module demux_final_1 $end
$var wire 1 * valid $end
$var wire 1 $ reset $end
$var wire 8 : data_in [7:0] $end
$var wire 1 & clk_4f $end
$var reg 32 ; data_out [31:0] $end
$var reg 2 < selector [1:0] $end
$var reg 1 , valid_out $end
$upscope $end
$scope module mux_stp $end
$var wire 32 = lane_0 [31:0] $end
$var wire 32 > lane_1 [31:0] $end
$var wire 1 - valid_0 $end
$var wire 1 , valid_1 $end
$var wire 1 $ reset $end
$var wire 1 ( clk_2f $end
$var reg 32 ? data_output [31:0] $end
$var reg 1 @ sel $end
$var reg 1 ! valid_out $end
$upscope $end
$scope module sp0 $end
$var wire 1 $ reset $end
$var wire 1 # data_in $end
$var wire 1 & clk_4f $end
$var wire 1 ' clk_32f $end
$var reg 3 A BC_counter [2:0] $end
$var reg 1 6 active $end
$var reg 8 B data2send [7:0] $end
$var reg 8 C data_out [7:0] $end
$var reg 1 D dataout_on $end
$var reg 3 E selector [2:0] $end
$var reg 8 F transicion_dataout [7:0] $end
$var reg 1 + valid_out $end
$upscope $end
$scope module sp1 $end
$var wire 1 $ reset $end
$var wire 1 " data_in $end
$var wire 1 & clk_4f $end
$var wire 1 ' clk_32f $end
$var reg 3 G BC_counter [2:0] $end
$var reg 1 5 active $end
$var reg 8 H data2send [7:0] $end
$var reg 8 I data_out [7:0] $end
$var reg 1 J dataout_on $end
$var reg 3 K selector [2:0] $end
$var reg 8 L transicion_dataout [7:0] $end
$var reg 1 * valid_out $end
$upscope $end
$upscope $end
$scope module probador $end
$var wire 32 M data_final [31:0] $end
$var wire 1 ! valid_final $end
$var reg 1 ( clk_2f $end
$var reg 1 ' clk_32f $end
$var reg 1 & clk_4f $end
$var reg 1 $ reset $end
$var reg 1 # serial_data_0 $end
$var reg 1 " serial_data_1 $end
$upscope $end
$upscope $end
$enddefinitions $end
#0
$dumpvars
b0 M
b0 L
b0 K
0J
b0 I
b0 H
b0 G
b0 F
b0 E
0D
b0 C
b0 B
b0 A
0@
b0 ?
b0 >
b0 =
b0 <
b0 ;
b0 :
b0 9
b0 8
b0 7
06
05
b0 4
b0 3
b0 2
b0 1
b0 0
b0 /
b0 .
0-
0,
0+
0*
z)
1(
1'
1&
b0 %
0$
1#
1"
0!
$end
#10
0'
#20
0"
0#
1'
#30
0'
#40
1"
1#
1'
#50
0'
#60
1'
#70
0'
#80
1'
0&
#90
0'
#100
1'
#110
0'
#120
0"
0#
1'
#130
0'
#140
1'
#150
0'
#160
1"
1#
1'
1&
0(
#170
0'
#180
0"
0#
1'
#190
0'
#200
1"
1#
1'
#210
0'
#220
1'
#230
0'
#240
1'
0&
#250
0'
#260
1'
#270
0'
#280
0"
0#
1'
#290
0'
#300
1'
#310
0'
#320
1"
1#
1$
1'
1&
1(
#330
0'
#340
0"
0#
b1 K
b10000000 3
b10000000 H
b1 E
b10000000 4
b10000000 B
1'
#350
0'
#360
b10 E
b10 K
1"
1#
1'
#370
0'
#380
b11 K
b10100000 3
b10100000 H
b11 E
b10100000 4
b10100000 B
1'
#390
0'
#400
b100 E
b10110000 4
b10110000 B
b100 K
b10110000 3
b10110000 H
1'
0&
#410
0'
#420
b101 K
b10111000 3
b10111000 H
b101 E
b10111000 4
b10111000 B
1'
#430
0'
#440
b110 E
b10111100 4
b10111100 B
b110 K
b10111100 3
b10111100 H
0"
0#
1'
#450
0'
#460
b111 K
b111 E
1'
#470
0'
#480
b1 A
b0 E
b1 G
b0 K
1"
1#
1'
1&
0(
#490
0'
#500
0"
0#
b1 K
b1 E
1'
#510
0'
#520
b10 E
b10 K
1"
1#
1'
#530
0'
#540
b11 K
b11 E
1'
#550
0'
#560
b100 E
b100 K
1'
0&
#570
0'
#580
b101 K
b101 E
1'
#590
0'
#600
b110 E
b110 K
0"
0#
1'
#610
0'
#620
b111 K
b111 E
1'
#630
0'
#640
b10 A
b0 E
b10 G
b0 K
1"
1#
1'
1&
1(
#650
0'
#660
0"
0#
b1 K
b1 E
1'
#670
0'
#680
b10 E
b10 K
1"
1#
1'
#690
0'
#700
b11 K
b11 E
1'
#710
0'
#720
b100 E
b100 K
1'
0&
#730
0'
#740
b101 K
b101 E
1'
#750
0'
#760
b110 E
b110 K
0"
0#
1'
#770
0'
#780
b111 K
b111 E
1'
#790
0'
#800
b11 A
b0 E
b11 G
b0 K
1"
1#
1'
1&
0(
#810
0'
#820
0"
0#
b1 K
b1 E
1'
#830
0'
#840
b10 E
b10 K
1"
1#
1'
#850
0'
#860
b11 K
b11 E
1'
#870
0'
#880
b100 E
b100 K
1'
0&
#890
0'
#900
b101 K
b101 E
1'
#910
0'
#920
b110 E
b110 K
0"
0#
1'
#930
0'
#940
b111 K
b111 E
1'
#950
0'
#960
b100 A
b0 E
b100 G
b0 K
1"
1#
1'
1&
1(
#970
0'
#980
0"
0#
b1 K
b1 E
1'
#990
0'
#1000
b10 E
b10 K
1"
1#
1'
#1010
0'
#1020
b11 K
b11 E
1'
#1030
0'
#1040
b100 E
b100 K
1'
0&
#1050
0'
#1060
b101 K
b101 E
1'
#1070
0'
#1080
b110 E
b110 K
0"
0#
1'
#1090
0'
#1100
b111 K
b111 E
1'
#1110
0'
#1120
16
b101 A
b0 E
15
b101 G
b0 K
1"
1#
1'
1&
0(
#1130
0'
#1140
b1 K
b1 E
1'
#1150
0'
#1160
b10 E
b11111100 4
b11111100 B
b10 K
b11111100 3
b11111100 H
1'
#1170
0'
#1180
b11 K
b11 E
1'
#1190
0'
#1200
b100 E
b100 K
0"
0#
1'
0&
#1210
0'
#1220
b101 K
b11110100 3
b11110100 H
b101 E
b11110100 4
b11110100 B
1'
#1230
0'
#1240
b110 E
b11110000 4
b11110000 B
b110 K
b11110000 3
b11110000 H
1'
#1250
0'
#1260
b111 K
b111 E
1'
#1270
0'
#1280
1D
1+
b0 E
1J
1*
b0 K
1"
1#
1'
1&
1(
#1290
0'
#1300
b1 K
b10000000 L
b1 E
b10000000 F
1'
#1310
0'
#1320
b10 E
b11000000 F
b10 K
b11000000 L
1'
#1330
0'
#1340
b11 K
b11100000 L
b11 E
b11100000 F
1'
#1350
0'
#1360
b100 E
b11110000 F
b100 K
b11110000 L
0"
0#
1'
0&
#1370
0'
#1380
b101 K
b101 E
1'
#1390
0'
#1400
b110 E
b110 K
1'
#1410
0'
#1420
b111 K
b111 E
1'
#1430
0'
#1440
b11110000 1
b11110000 7
b11110000 C
b0 E
b11110000 0
b11110000 :
b11110000 I
b0 K
b1 <
1,
1"
1#
1'
1&
0(
#1450
0'
#1460
b1 K
b1 E
1'
#1470
0'
#1480
b10 E
b10 K
1'
#1490
0'
#1500
b11 K
b11 E
1'
#1510
0'
#1520
b100 E
b100 K
0"
0#
1'
0&
#1530
0'
#1540
b101 K
b101 E
1'
#1550
0'
#1560
b110 E
b110 K
1'
#1570
0'
#1580
b111 K
b111 E
1'
#1590
0'
#1600
b0 E
b0 K
b10 <
b111100000000000000000000 .
b111100000000000000000000 ;
b111100000000000000000000 >
1'
1&
1(
#1610
0'
#1620
b1 K
b1110000 L
b1110000 3
b1110000 H
b1 E
b1110000 F
b1110000 4
b1110000 B
1'
#1630
0'
#1640
b10 E
b110000 F
b110000 4
b110000 B
b10 K
b110000 L
b110000 3
b110000 H
1'
#1650
0'
#1660
b11 K
b10000 L
b10000 3
b10000 H
b11 E
b10000 F
b10000 4
b10000 B
1'
#1670
0'
#1680
b100 E
b0 F
b0 4
b0 B
b100 K
b0 L
b0 3
b0 H
1"
1#
1'
0&
#1690
0'
#1700
b101 K
b1000 L
b1000 3
b1000 H
b101 E
b1000 F
b1000 4
b1000 B
1'
#1710
0'
#1720
b110 E
b1100 F
b1100 4
b1100 B
b110 K
b1100 L
b1100 3
b1100 H
1'
#1730
0'
#1740
b111 K
b1110 L
b1110 3
b1110 H
b111 E
b1110 F
b1110 4
b1110 B
1'
#1750
0'
#1760
b1110 1
b1110 7
b1110 C
b0 E
b1111 F
b1111 4
b1111 B
b1110 0
b1110 :
b1110 I
b0 K
b1111 L
b1111 3
b1111 H
b11 <
b111100001111000000000000 .
b111100001111000000000000 ;
b111100001111000000000000 >
0"
0#
1'
1&
0(
#1770
0'
#1780
b1 K
b1 E
1'
#1790
0'
#1800
b10 E
b10 K
1'
#1810
0'
#1820
b11 K
b11 E
1'
#1830
0'
#1840
b100 E
b100 K
1"
1#
1'
0&
#1850
0'
#1860
b101 K
b101 E
1'
#1870
0'
#1880
b110 E
b110 K
1'
#1890
0'
#1900
b111 K
b111 E
1'
#1910
0'
#1920
b1111 1
b1111 7
b1111 C
b0 E
b1111 0
b1111 :
b1111 I
b0 K
b0 <
b111100001111000000001110 .
b111100001111000000001110 ;
b111100001111000000001110 >
1'
1&
1(
