demux_striping/probador_demux_striping.v
module probador_demux_striping( input [31:0] lane_0,
                        input [31:0] lane_1,
						input valid_out0,
                        input valid_out1,
						output reg valid_0,  
						output reg valid_1,
						output reg clk_2f,
						output reg [31:0] data_input);
	initial begin
	$dumpfile("demux_striping.vcd");
	$dumpvars;

	{valid_0,valid_1} <= 0;
	{data_input} <= 32'h00000000;
	
	@(posedge clk_2f);
	valid_0 <= 0;
    valid_1 <= 0;
	data_input <= 32'hFFFFFFFF;

	@(posedge clk_2f);
	valid_0 <= 1;
    valid_1 <= 1;
	data_input <= 32'hAAAAAAAA;

	@(posedge clk_2f);
	valid_0 <= 1;
    valid_1 <= 1;
	data_input <= 32'hEEEEEEEE;

	@(posedge clk_2f);
	valid_0 <= 1;
    valid_1 <= 1;
	data_input <= 32'hCCCCCCCCCC;

	@(posedge clk_2f);
	valid_0 <= 1;
    valid_1 <= 1;
	data_input <= 32'hAAAAAAAA;

	@(posedge clk_2f);
	valid_0 <= 1;
    valid_1 <= 1;
	data_input <= 32'h11111111;

	@(posedge clk_2f);
	valid_0 <= 1;
    valid_1 <= 1;
	data_input <= 32'h99999999;

	@(posedge clk_2f);

	@(posedge clk_2f);
	$finish;
	end
	
	initial clk_2f <= 0;
	always #2 clk_2f <= ~clk_2f;


endmodule

demux_striping/demux_striping.v
module demux_striping(
    input clk_2f,
	input [31:0] data_input,
	input valid_0,
    input valid_1,
	output reg [31:0] lane_0,
	output reg [31:0] lane_1,
    output reg  valid_out0,
    output reg valid_out1
    );
    reg sel= 0;

	always @(posedge clk_2f) begin
		if(valid_0 == 1 && sel == 0 ) begin
			lane_0 <= data_input;
			sel <= 1;
            valid_out0<=1;
		end

		else if(valid_1 == 1 || sel == 1) begin
			lane_1 <= data_input;
			sel <= 0;
            valid_out1<=1;
		end
	end

endmodule

demux_striping/banco_demux_striping.v
`timescale 1ms/100ps

`include "probador_demux_striping.v"
`include "demux_striping.v"

module banco_demux_striping;
	wire [31:0] data_input, lane_0, lane_1;
	wire clk_2f, valid_out0, valid_out1, valid_0, valid_1;


	demux_striping demuxs(/*AUTOINST*/
			      // Outputs
			      .lane_0		(lane_0[31:0]),
			      .lane_1		(lane_1[31:0]),
			      .valid_out0	(valid_out0),
			      .valid_out1	(valid_out1),
			      // Inputs
			      .clk_2f		(clk_2f),
			      .data_input	(data_input[31:0]),
			      .valid_0		(valid_0),
			      .valid_1		(valid_1));


	probador_demux_striping probador(/*AUTOINST*/
					 // Outputs
					 .valid_0		(valid_0),
					 .valid_1		(valid_1),
					 .clk_2f		(clk_2f),
					 // Inputs
					 .lane_0		(lane_0[31:0]),
					 .lane_1		(lane_1[31:0]),
					 .data_input		(data_input[31:0]),
					 .valid_out0		(valid_out0),
					 .valid_out1		(valid_out1));


endmodule

demux_striping/demux_striping.vcd
$date
	Mon Sep 21 01:30:18 2020
$end
$version
	Icarus Verilog
$end
$timescale
	100ps
$end
$scope module banco_demux_striping $end
$var wire 1 ! valid_out1 $end
$var wire 1 " valid_out0 $end
$var wire 1 # valid_1 $end
$var wire 1 $ valid_0 $end
$var wire 32 % lane_1 [31:0] $end
$var wire 32 & lane_0 [31:0] $end
$var wire 32 ' data_input [31:0] $end
$var wire 1 ( clk_2f $end
$scope module demuxs $end
$var wire 1 # valid_1 $end
$var wire 1 $ valid_0 $end
$var wire 32 ) data_input [31:0] $end
$var wire 1 ( clk_2f $end
$var reg 32 * lane_0 [31:0] $end
$var reg 32 + lane_1 [31:0] $end
$var reg 1 , sel $end
$var reg 1 " valid_out0 $end
$var reg 1 ! valid_out1 $end
$upscope $end
$scope module probador $end
$var wire 32 - lane_0 [31:0] $end
$var wire 32 . lane_1 [31:0] $end
$var wire 1 " valid_out0 $end
$var wire 1 ! valid_out1 $end
$var reg 1 ( clk_2f $end
$var reg 32 / data_input [31:0] $end
$var reg 1 $ valid_0 $end
$var reg 1 # valid_1 $end
$upscope $end
$upscope $end
$enddefinitions $end
#0
$dumpvars
b0 /
bx .
bx -
0,
bx +
bx *
b0 )
0(
b0 '
bx &
bx %
0$
0#
x"
x!
$end
#20000000
b11111111111111111111111111111111 '
b11111111111111111111111111111111 )
b11111111111111111111111111111111 /
1(
#40000000
0(
#60000000
b10101010101010101010101010101010 '
b10101010101010101010101010101010 )
b10101010101010101010101010101010 /
1#
1$
1(
#80000000
0(
#100000000
1"
1,
b10101010101010101010101010101010 &
b10101010101010101010101010101010 *
b10101010101010101010101010101010 -
b11101110111011101110111011101110 '
b11101110111011101110111011101110 )
b11101110111011101110111011101110 /
1(
#120000000
0(
#140000000
b11001100110011001100110011001100 '
b11001100110011001100110011001100 )
b11001100110011001100110011001100 /
1!
0,
b11101110111011101110111011101110 %
b11101110111011101110111011101110 +
b11101110111011101110111011101110 .
1(
#160000000
0(
#180000000
1,
b11001100110011001100110011001100 &
b11001100110011001100110011001100 *
b11001100110011001100110011001100 -
b10101010101010101010101010101010 '
b10101010101010101010101010101010 )
b10101010101010101010101010101010 /
1(
#200000000
0(
#220000000
b10001000100010001000100010001 '
b10001000100010001000100010001 )
b10001000100010001000100010001 /
0,
b10101010101010101010101010101010 %
b10101010101010101010101010101010 +
b10101010101010101010101010101010 .
1(
#240000000
0(
#260000000
1,
b10001000100010001000100010001 &
b10001000100010001000100010001 *
b10001000100010001000100010001 -
b10011001100110011001100110011001 '
b10011001100110011001100110011001 )
b10011001100110011001100110011001 /
1(
#280000000
0(
#300000000
0,
b10011001100110011001100110011001 %
b10011001100110011001100110011001 +
b10011001100110011001100110011001 .
1(
#320000000
0(
#340000000
1,
b10011001100110011001100110011001 &
b10011001100110011001100110011001 *
b10011001100110011001100110011001 -
1(
