paralelo_serial_2/probador_paralelo_serial0.v
module probador_paralelo_serial0(input [7:0] data2send,
                                input data_out,
								input data_out_fin,
								output reg reset,
								output reg valid_in,
						        output reg [7:0] data_in,
						        output reg clk_4f,
						        output reg clk_32f);
	initial begin
	$dumpfile("paraleloserial.vcd");
	$dumpvars;

	{valid_in} <= 0;
	data_in <= 8'hFF;
	reset <=0;
	
	@(posedge clk_4f);
	valid_in <= 0;
	data_in <= 8'hDE;
	reset <= 0;

	@(posedge clk_4f);
	valid_in <= 0;
	data_in <= 8'hCC;
	@(posedge clk_4f);
	reset <=1;
	valid_in <= 1;
	data_in <= 8'hAB;

	@(posedge clk_4f);
	valid_in <= 1;
	data_in <= 8'hCA;

	@(posedge clk_4f);
	valid_in <= 1;
	data_in <= 8'h12;

	@(posedge clk_4f);
	valid_in <= 0;
	data_in <= 8'hDC;

	@(posedge clk_4f);
	valid_in <= 1;
	data_in <= 8'hFA;

	@(posedge clk_4f);
	valid_in <= 1;
	data_in <= 8'h33;
	@(posedge clk_4f);
	$finish;
	end
	
	initial clk_4f <= 1;
	always #8 clk_4f <= ~clk_4f;

	initial clk_32f <= 1;
	always #1 clk_32f <= ~clk_32f;


endmodule

paralelo_serial_2/paralelo_serial1.v
module paralelo_serial1(input clk_32f,
                        input [7:0] data2send,
                        input reset,
                        output reg data_out);

    reg [2:0] selector;

    always @(posedge clk_32f) begin
            if (reset==0)begin
                selector <= 3'b111;
            end
            else if (reset == 1)begin
                if (selector==3'b111) begin
                    data_out <= data2send[7];
                    selector <= 3'b110;
                end
                else if (selector==3'b110) begin
                    data_out <= data2send[6];
                    selector <= 3'b101;
                end            
                else if (selector==3'b101) begin
                    data_out <= data2send[5];
                    selector <= 3'b100;
                end
                else if (selector==3'b100) begin
                    data_out <= data2send[4];
                    selector <= 3'b011;
                end 
                else if (selector==3'b011) begin
                    data_out <= data2send[3];
                    selector <= 3'b010;
                end 
                else if (selector==3'b010) begin
                    data_out <= data2send[2];
                    selector <= 3'b001;
                end 
                else if (selector==3'b001) begin
                    data_out <= data2send[1];
                    selector <= 3'b000;
                end 
                else if (selector==3'b000) begin
                    data_out <= data2send[0];
                    selector <= 3'b111;
                end 
            end
   
    end
endmodule

paralelo_serial_2/paralelo_serial0.v
module paralelo_serial0(input clk_4f,
                        input [7:0] data_in,
                        input valid_in,
                        output reg [7:0] data2send);
    always @(posedge clk_4f)begin
        if (valid_in==0)begin
            data2send <= 8'hBC;
        end
        else begin
            data2send <= data_in;
        end 
    end
endmodule

paralelo_serial_2/paralelo_serial.v
`include "paralelo_serial0.v"
`include "paralelo_serial1.v"

module paralelo_serial(input [7:0] data_in, 
                        input valid_in,
                        input reset,
                        input clk_4f,
                        input clk_32f,
                        output data_out_fin);
    wire [7:0] cable;
    
    paralelo_serial0 parte0(.clk_4f(clk_4f), .data_in(data_in), .valid_in(valid_in), .data2send(cable));

    paralelo_serial1 parte1(.clk_32f(clk_32f), .data2send(cable),.reset (reset), .data_out(data_out_fin));

endmodule

paralelo_serial_2/banco_paralelo_serial0.v
`timescale 1ms/100ps

`include "paralelo_serial.v"
`include "probador_paralelo_serial0.v"

    module banco_paralelo_serial0;
        wire [7:0] data_in, data2send;
        wire clk_4f, clk_32f, valid_in, data_out, data_out_fin, reset;

        paralelo_serial paraleloserial(
                                        .data_out_fin(data_out_fin),
                                        .data_in(data_in),
                                        .valid_in(valid_in),
                                        .reset (reset),
                                        .clk_32f(clk_32f),
                                        .clk_4f(clk_4f));

        paralelo_serial0 paraleloserial0(/*AUTOINST*/
					 // Outputs
					 .data2send		(data2send[7:0]),
					 // Inputs
					 .clk_4f		(clk_4f),
					 .data_in		(data_in[7:0]),
					 .valid_in		(valid_in));

        paralelo_serial1 paraleloserial1(.data_out(data_out),
                                        .clk_32f(clk_32f),
                                        .data2send(data_in));

        probador_paralelo_serial0 probador0(/*AUTOINST*/
					    // Outputs
					    .reset		(reset),
					    .valid_in		(valid_in),
                        .data_out (data_out),
					    .data_in		(data_in[7:0]),
					    .clk_4f		(clk_4f),
					    .clk_32f		(clk_32f),
					    // Inputs
					    .data2send		(data2send[7:0]));
    
    endmodule

paralelo_serial_2/paraleloserial.vcd
$date
	Sat Sep 26 12:38:04 2020
$end
$version
	Icarus Verilog
$end
$timescale
	100ps
$end
$scope module banco_paralelo_serial0 $end
$var wire 1 ! valid_in $end
$var wire 1 " reset $end
$var wire 1 # data_out_fin $end
$var wire 1 $ data_out $end
$var wire 8 % data_in [7:0] $end
$var wire 8 & data2send [7:0] $end
$var wire 1 ' clk_4f $end
$var wire 1 ( clk_32f $end
$scope module paraleloserial $end
$var wire 1 ! valid_in $end
$var wire 1 " reset $end
$var wire 1 # data_out_fin $end
$var wire 8 ) data_in [7:0] $end
$var wire 1 ' clk_4f $end
$var wire 1 ( clk_32f $end
$var wire 8 * cable [7:0] $end
$scope module parte0 $end
$var wire 1 ! valid_in $end
$var wire 8 + data_in [7:0] $end
$var wire 1 ' clk_4f $end
$var reg 8 , data2send [7:0] $end
$upscope $end
$scope module parte1 $end
$var wire 8 - data2send [7:0] $end
$var wire 1 " reset $end
$var wire 1 ( clk_32f $end
$var reg 1 # data_out $end
$var reg 3 . selector [2:0] $end
$upscope $end
$upscope $end
$scope module paraleloserial0 $end
$var wire 1 ! valid_in $end
$var wire 8 / data_in [7:0] $end
$var wire 1 ' clk_4f $end
$var reg 8 0 data2send [7:0] $end
$upscope $end
$scope module paraleloserial1 $end
$var wire 1 1 reset $end
$var wire 8 2 data2send [7:0] $end
$var wire 1 ( clk_32f $end
$var reg 1 $ data_out $end
$var reg 3 3 selector [2:0] $end
$upscope $end
$scope module probador0 $end
$var wire 8 4 data2send [7:0] $end
$var wire 1 $ data_out $end
$var wire 1 5 data_out_fin $end
$var reg 1 ( clk_32f $end
$var reg 1 ' clk_4f $end
$var reg 8 6 data_in [7:0] $end
$var reg 1 " reset $end
$var reg 1 ! valid_in $end
$upscope $end
$upscope $end
$enddefinitions $end
#0
$dumpvars
b11011110 6
z5
b10111100 4
bx 3
b11011110 2
z1
b10111100 0
b11011110 /
b111 .
b10111100 -
b10111100 ,
b11011110 +
b10111100 *
b11011110 )
1(
1'
b10111100 &
b11011110 %
x$
x#
0"
0!
$end
#10000000
0(
#20000000
1(
#30000000
0(
#40000000
1(
#50000000
0(
#60000000
1(
#70000000
0(
#80000000
1(
0'
#90000000
0(
#100000000
1(
#110000000
0(
#120000000
1(
#130000000
0(
#140000000
1(
#150000000
0(
#160000000
b11001100 %
b11001100 )
b11001100 +
b11001100 /
b11001100 2
b11001100 6
1(
1'
#170000000
0(
#180000000
1(
#190000000
0(
#200000000
1(
#210000000
0(
#220000000
1(
#230000000
0(
#240000000
1(
0'
#250000000
0(
#260000000
1(
#270000000
0(
#280000000
1(
#290000000
0(
#300000000
1(
#310000000
0(
#320000000
b10101011 %
b10101011 )
b10101011 +
b10101011 /
b10101011 2
b10101011 6
1!
1"
1(
1'
#330000000
0(
#340000000
b110 .
1#
1(
#350000000
0(
#360000000
b101 .
0#
1(
#370000000
0(
#380000000
b100 .
1#
1(
#390000000
0(
#400000000
b11 .
1(
0'
#410000000
0(
#420000000
b10 .
1(
#430000000
0(
#440000000
b1 .
1(
#450000000
0(
#460000000
b0 .
0#
1(
#470000000
0(
#480000000
b111 .
b11001010 %
b11001010 )
b11001010 +
b11001010 /
b11001010 2
b11001010 6
b10101011 &
b10101011 0
b10101011 4
b10101011 *
b10101011 ,
b10101011 -
1(
1'
#490000000
0(
#500000000
b110 .
1#
1(
#510000000
0(
#520000000
b101 .
0#
1(
#530000000
0(
#540000000
b100 .
1#
1(
#550000000
0(
#560000000
b11 .
0#
1(
0'
#570000000
0(
#580000000
b10 .
1#
1(
#590000000
0(
#600000000
b1 .
0#
1(
#610000000
0(
#620000000
b0 .
1#
1(
#630000000
0(
#640000000
b111 .
b11001010 *
b11001010 ,
b11001010 -
b11001010 &
b11001010 0
b11001010 4
b10010 %
b10010 )
b10010 +
b10010 /
b10010 2
b10010 6
1(
1'
#650000000
0(
#660000000
b110 .
1(
#670000000
0(
#680000000
b101 .
1(
#690000000
0(
#700000000
b100 .
0#
1(
#710000000
0(
#720000000
b11 .
1(
0'
#730000000
0(
#740000000
b10 .
1#
1(
#750000000
0(
#760000000
b1 .
0#
1(
#770000000
0(
#780000000
b0 .
1#
1(
#790000000
0(
#800000000
b111 .
0#
b11011100 %
b11011100 )
b11011100 +
b11011100 /
b11011100 2
b11011100 6
0!
b10010 &
b10010 0
b10010 4
b10010 *
b10010 ,
b10010 -
1(
1'
#810000000
0(
#820000000
b110 .
1(
#830000000
0(
#840000000
b101 .
1(
#850000000
0(
#860000000
b100 .
1(
#870000000
0(
#880000000
b11 .
1#
1(
0'
#890000000
0(
#900000000
b10 .
0#
1(
#910000000
0(
#920000000
b1 .
1(
#930000000
0(
#940000000
b0 .
1#
1(
#950000000
0(
#960000000
b111 .
0#
b10111100 *
b10111100 ,
b10111100 -
b10111100 &
b10111100 0
b10111100 4
b11111010 %
b11111010 )
b11111010 +
b11111010 /
b11111010 2
b11111010 6
1!
1(
1'
#970000000
0(
#980000000
b110 .
1#
1(
#990000000
0(
#1000000000
b101 .
0#
1(
#1010000000
0(
#1020000000
b100 .
1#
1(
#1030000000
0(
#1040000000
b11 .
1(
0'
#1050000000
0(
#1060000000
b10 .
1(
#1070000000
0(
#1080000000
b1 .
1(
#1090000000
0(
#1100000000
b0 .
0#
1(
#1110000000
0(
#1120000000
b111 .
b110011 %
b110011 )
b110011 +
b110011 /
b110011 2
b110011 6
b11111010 &
b11111010 0
b11111010 4
b11111010 *
b11111010 ,
b11111010 -
1(
1'
#1130000000
0(
#1140000000
b110 .
1#
1(
#1150000000
0(
#1160000000
b101 .
1(
#1170000000
0(
#1180000000
b100 .
1(
#1190000000
0(
#1200000000
b11 .
1(
0'
#1210000000
0(
#1220000000
b10 .
1(
#1230000000
0(
#1240000000
b1 .
0#
1(
#1250000000
0(
#1260000000
b0 .
1#
1(
#1270000000
0(
#1280000000
b111 .
0#
b110011 *
b110011 ,
b110011 -
b110011 &
b110011 0
b110011 4
1(
1'
