recirculacion/probador_recirc.v
module probador_recirc(input [31:0] demux_0,
						input [31:0] demux_1_probador,
						input valid_out,
						output reg active,
						output reg valid,
						output reg [31:0] data_input,
						output reg clk_2f);
	initial begin
	$dumpfile("recirculacion.vcd");
	$dumpvars;

	{valid, active} <= 0;
	{data_input} <= 32'h00000000;
	
	@(posedge clk_2f);
	active <= 1;
	valid <= 0;
	data_input <= 32'hFFFFEEEE;

	@(posedge clk_2f);
	active <= 1;
	valid <= 1;
	data_input <= 32'hFFEEEEEE;

	@(posedge clk_2f);
	active <= 1;
	valid <= 1;
	data_input <= 32'hFFEEEEEE;

	@(posedge clk_2f);
	active <= 1;
	valid <= 0;
	data_input <= 32'hCCEEEEEE;

	@(posedge clk_2f);
	active <= 1;
	valid <= 1;
	data_input <= 32'hAAAA1234;

	@(posedge clk_2f);
	active <= 0;
	valid <= 1;
	data_input <= 32'h12345678;

	@(posedge clk_2f);
	active <= 0;
	valid <= 1;
	data_input <= 32'hBBBBAAAA;

	@(posedge clk_2f);

	@(posedge clk_2f);
	$finish;
	end
	
	initial clk_2f <= 0;
	always #2 clk_2f <= ~clk_2f;


endmodule

recirculacion/recirculador.v
module recirculador(input clk_2f,
					input [31:0] data_input,
					input valid,
					input active,
					output reg [31:0] demux_0,
					output reg [31:0] demux_1_probador,
					output reg valid_out);

	always @(posedge clk_2f) begin
		if(valid == 1 && active == 1) begin
			demux_0 <= data_input;
			valid_out <= 1;
		end

		else if(valid == 0 || active == 0) begin
			demux_1_probador <= data_input;
			valid_out <= 0;
		end
	end

endmodule

recirculacion/banco_recirculacion.v
`timescale 1ms/100ps

`include "probador_recirc.v"
`include "recirculacion.v"

module BancoPruebas_recirc;
	wire [31:0] data_input, demux_0, demux_1_probador;
	wire clk_2f, valid_circulacion, active;


	recirculador p_recirculador(
    .clk_2f            ( clk_2f            ),
    .data_input        ( data_input [31:0] ),
    .valid			   ( valid			   ),
    .active            ( active            ),
    .demux_0           ( demux_0    [31:0] ),
    .demux_1_probador  ( demux_1_probador [31:0] ),
	.valid_out			(valid_out)
	);


	probador_recirc probador(
    .data_input       ( data_input [31:0]),
    .demux_0          ( demux_0          [31:0]),
    .demux_1_probador ( demux_1_probador [31:0]),
    .valid_out        ( valid_out        ),
    .active           ( active           ),
    .valid            ( valid            ),
    .clk_2f           ( clk_2f           )
	);


endmodule

recirculacion/recirculacion.vcd
$date
	Sun Sep 20 18:44:34 2020
$end
$version
	Icarus Verilog
$end
$timescale
	100ps
$end
$scope module BancoPruebas_recirc $end
$var wire 1 ! valid_out $end
$var wire 1 " valid $end
$var wire 32 # demux_1_probador [31:0] $end
$var wire 32 $ demux_0 [31:0] $end
$var wire 32 % data_input [31:0] $end
$var wire 1 & clk_2f $end
$var wire 1 ' active $end
$scope module p_recirculador $end
$var wire 1 " valid $end
$var wire 32 ( data_input [31:0] $end
$var wire 1 & clk_2f $end
$var wire 1 ' active $end
$var reg 32 ) demux_0 [31:0] $end
$var reg 32 * demux_1_probador [31:0] $end
$var reg 1 ! valid_out $end
$upscope $end
$scope module probador $end
$var wire 32 + demux_0 [31:0] $end
$var wire 32 , demux_1_probador [31:0] $end
$var wire 1 ! valid_out $end
$var reg 1 ' active $end
$var reg 1 & clk_2f $end
$var reg 32 - data_input [31:0] $end
$var reg 1 " valid $end
$upscope $end
$upscope $end
$enddefinitions $end
#0
$dumpvars
b0 -
bx ,
bx +
bx *
bx )
b0 (
0'
0&
b0 %
bx $
bx #
0"
x!
$end
#20000000
0!
b0 #
b0 *
b0 ,
b11111111111111111110111011101110 %
b11111111111111111110111011101110 (
b11111111111111111110111011101110 -
1'
1&
#40000000
0&
#60000000
b11111111111011101110111011101110 %
b11111111111011101110111011101110 (
b11111111111011101110111011101110 -
1"
b11111111111111111110111011101110 #
b11111111111111111110111011101110 *
b11111111111111111110111011101110 ,
1&
#80000000
0&
#100000000
1!
b11111111111011101110111011101110 $
b11111111111011101110111011101110 )
b11111111111011101110111011101110 +
1&
#120000000
0&
#140000000
b11001100111011101110111011101110 %
b11001100111011101110111011101110 (
b11001100111011101110111011101110 -
0"
1&
#160000000
0&
#180000000
0!
b11001100111011101110111011101110 #
b11001100111011101110111011101110 *
b11001100111011101110111011101110 ,
b10101010101010100001001000110100 %
b10101010101010100001001000110100 (
b10101010101010100001001000110100 -
1"
1&
#200000000
0&
#220000000
b10010001101000101011001111000 %
b10010001101000101011001111000 (
b10010001101000101011001111000 -
0'
1!
b10101010101010100001001000110100 $
b10101010101010100001001000110100 )
b10101010101010100001001000110100 +
1&
#240000000
0&
#260000000
0!
b10010001101000101011001111000 #
b10010001101000101011001111000 *
b10010001101000101011001111000 ,
b10111011101110111010101010101010 %
b10111011101110111010101010101010 (
b10111011101110111010101010101010 -
1&
#280000000
0&
#300000000
b10111011101110111010101010101010 #
b10111011101110111010101010101010 *
b10111011101110111010101010101010 ,
1&
